maestral/__init__.py
maestral/__main__.py
maestral/autostart.py
maestral/client.py
maestral/constants.py
maestral/core.py
maestral/daemon.py
maestral/errorhandling.py
maestral/exceptions.py
maestral/keyring.py
maestral/logging.py
maestral/main.py
maestral/manager.py
maestral/models.py
maestral/notify.py
maestral/py.typed
maestral/sync.py
maestral/cli/__init__.py
maestral/cli/cli_core.py
maestral/cli/cli_info.py
maestral/cli/cli_main.py
maestral/cli/cli_maintenance.py
maestral/cli/cli_settings.py
maestral/cli/common.py
maestral/cli/core.py
maestral/cli/dialogs.py
maestral/cli/output.py
maestral/cli/utils.py
maestral/config/__init__.py
maestral/config/main.py
maestral/config/user.py
maestral/database/__init__.py
maestral/database/core.py
maestral/database/orm.py
maestral/database/query.py
maestral/database/types.py
maestral/fsevents/__init__.py
maestral/fsevents/polling.py
maestral/resources/__init__.py
maestral/resources/maestral.png
maestral/utils/__init__.py
maestral/utils/appdirs.py
maestral/utils/caches.py
maestral/utils/hashing.py
maestral/utils/integration.py
maestral/utils/path.py
maestral-1.9.6.data/data/share/icons/hicolor/512x512/apps/maestral.png
maestral-1.9.6.dist-info/licenses/LICENSE.txt
maestral-1.9.6.dist-info/METADATA
maestral-1.9.6.dist-info/WHEEL
maestral-1.9.6.dist-info/entry_points.txt
maestral-1.9.6.dist-info/top_level.txt
maestral-1.9.6.dist-info/RECORD
