Metadata-Version: 2.4
Name: maestral
Version: 1.9.6
Summary: Open-source Dropbox client for macOS and Linux.
Author-email: Sam Schott <sam.schott@outlook.com>
License: MIT
Project-URL: Homepage, https://maestral.app
Classifier: License :: OSI Approved :: MIT License
Classifier: Operating System :: Unix
Classifier: Programming Language :: Python
Classifier: Programming Language :: Python :: 3
Classifier: Programming Language :: Python :: 3.10
Classifier: Programming Language :: Python :: 3.11
Classifier: Programming Language :: Python :: 3.12
Classifier: Programming Language :: Python :: 3.13
Classifier: Programming Language :: Python :: 3 :: Only
Requires-Python: >=3.10
License-File: LICENSE.txt
Requires-Dist: click>=8.2.0
Requires-Dist: desktop-notifier>=5.0.0
Requires-Dist: dropbox<13.0,>=11.28.0
Requires-Dist: fasteners>=0.15
Requires-Dist: keyring>=22
Requires-Dist: keyrings.alt>=3.1.0
Requires-Dist: packaging
Requires-Dist: pathspec>=0.5.8
Requires-Dist: Pyro5>=5.10
Requires-Dist: requests>=2.16.2
Requires-Dist: rich
Requires-Dist: rubicon-objc>=0.4.1; sys_platform == "darwin"
Requires-Dist: setuptools
Requires-Dist: survey<6.0,>=4.0
Requires-Dist: typing_extensions
Requires-Dist: watchdog>=2.0.1
Requires-Dist: xattr
Provides-Extra: gui
Requires-Dist: maestral-qt>=1.9.6; sys_platform == "linux" and extra == "gui"
Requires-Dist: maestral-cocoa>=1.9.6; sys_platform == "darwin" and extra == "gui"
Provides-Extra: syslog
Requires-Dist: systemd-python; extra == "syslog"
Provides-Extra: lint
Requires-Dist: black; extra == "lint"
Requires-Dist: flake8; extra == "lint"
Requires-Dist: flake8-pyproject; extra == "lint"
Requires-Dist: isort; extra == "lint"
Requires-Dist: mypy; extra == "lint"
Requires-Dist: pyupgrade; extra == "lint"
Requires-Dist: types-requests; extra == "lint"
Requires-Dist: types-setuptools; extra == "lint"
Provides-Extra: test
Requires-Dist: pytest; extra == "test"
Requires-Dist: pytest-benchmark; extra == "test"
Requires-Dist: pytest-cov; extra == "test"
Requires-Dist: pytest-rerunfailures; extra == "test"
Provides-Extra: docs
Requires-Dist: furo==2025.9.25; extra == "docs"
Requires-Dist: sphinx==8.1.3; extra == "docs"
Requires-Dist: sphinxext-opengraph==0.13.0; extra == "docs"
Requires-Dist: sphinx-autoapi==3.6.1; extra == "docs"
Requires-Dist: sphinx-mdinclude==0.6.2; extra == "docs"
Provides-Extra: dev
Requires-Dist: bump2version; extra == "dev"
Requires-Dist: maestral[lint,test]; extra == "dev"
Dynamic: license-file
